Metadata-Version: 1.1
Name: bibcat
Version: 2.3.1
Summary: BIBCAT RDF Framework Application
Home-page: http://knowledgelinks.io/#/products/bibcat
Author: KnowledgeLinks
Author-email: knowledgelinks.io@gmail.com
License: MIT
Keywords: semantic web bibframe rdf
Platform: UNKNOWN
Classifier: Development Status :: 4 - Beta
Classifier: Intended Audience :: Developers
Classifier: License :: OSI Approved :: MIT License
Classifier: Programming Language :: Python :: 3
Classifier: Topic :: Database
Classifier: Topic :: Text Processing :: General
Classifier: Topic :: Text Processing :: Indexing
